{
  "programs": [
    {
      "mode": 3,
      "name": "start",
      "nodes": []
    },
    {
      "mode": 3,
      "name": "MoveRobot",
      "nodes": [
        {
          "start": 126,
          "end": 1015,
          "isCollapsed": false
        },
        {
          "start": 367,
          "end": 995,
          "isCollapsed": false
        },
        {
          "start": 393,
          "end": 932,
          "isCollapsed": false
        },
        {
          "start": 418,
          "end": 516,
          "isCollapsed": false
        },
        {
          "start": 525,
          "end": 621,
          "isCollapsed": false
        },
        {
          "start": 630,
          "end": 727,
          "isCollapsed": false
        },
        {
          "start": 736,
          "end": 833,
          "isCollapsed": false
        },
        {
          "start": 842,
          "end": 916,
          "isCollapsed": false
        }
      ]
    },
    {
      "mode": 3,
      "name": "pantalla",
      "nodes": [
        {
          "start": 135,
          "end": 687,
          "isCollapsed": false
        },
        {
          "start": 227,
          "end": 535,
          "isCollapsed": false
        },
        {
          "start": 252,
          "end": 315,
          "isCollapsed": false
        },
        {
          "start": 322,
          "end": 454,
          "isCollapsed": false
        },
        {
          "start": 461,
          "end": 521,
          "isCollapsed": false
        },
        {
          "start": 565,
          "end": 609,
          "isCollapsed": false
        }
      ]
    }
  ]
}